{"cameraMode":{"drawMode":0,"name":"Shaded","section":"Shading Mode"},"sceneLighting":false,"audioPlay":false,"sceneViewState":{"m_AlwaysRefresh":false,"showFog":true,"showSkybox":false,"showFlares":true,"showImageEffects":true,"showParticleSystems":true,"showVisualEffectGraphs":true,"m_FxEnabled":true},"in2DMode":false,"pivot":{"x":531.47998046875,"y":158.9600067138672,"z":670.0999755859375},"rotation":{"x":-0.1280750036239624,"y":0.8597820997238159,"z":-0.2635151743888855,"w":-0.4185863435268402},"size":0.6578361988067627,"orthographic":false}